{
  "url": "https://tamu-csm.symplicity.com/events/4e14310febad2eb8767770a213251a7f/employers/01f5016d99e193977c1bf344ba0b0a15",
  "scraped_at": "2026-02-08T10:52:11.495065",
  "company_name": "1Finity, a Fujitsu Company",
  "about": "https://global.fujitsu/en-us/careers View full profile View all jobs\nThe Fujitsu Group has operations in different regions around the world, including Japan, and provides digital services globally. We have built large-scale, cutting-edge systems that leverage our advanced technologies and extensive track record, garnering the No. 1 market share in Japan and a top-class position worldwide in the IT services field. As of July 1st 2025, Fujitsu consolidated its network business into a new company, 1Finity. A wholly owned subsidiary of Fujitsu, 1Finity combines decades of trusted experience with renewed innovation, agility, and customer success 1Finity, a Fujitsu company, is a global provider of communications networks for our connected world. We uniquely combine technological leadership and expertise in open optical and wireless networking, network automation, and applied AI/ML to design, build, operate, and maintain critical digital communications network infrastructure.",
  "we_are_looking_for": "Industry\nEngineering\nDegree Levels Recruited\nBachelor's, Master's\nPosition Types\nFull-Time, Intern",
  "organization_profile": {
    "content": [
      "Website",
      "Overview",
      "The Fujitsu Group has operations in different regions around the world, including Japan, and provides digital services globally.",
      "We have built large-scale, cutting-edge systems that leverage our advanced technologies and extensive track record, garnering the No. 1 market share in Japan and a top-class position worldwide in the IT services field.",
      "",
      "As of July 1st 2025, Fujitsu consolidated its network business into a new company, 1Finity. A wholly owned subsidiary of Fujitsu, 1Finity combines decades of trusted experience with renewed innovation, agility, and customer success",
      "",
      "1Finity, a Fujitsu company, is a global provider of communications networks for our connected world. We uniquely combine technological leadership and expertise in open optical and wireless networking, network automation, and applied AI/ML to design, build, operate, and maintain critical digital communications network infrastructure.",
      "Major(s) Recruited",
      "Computer Engineering (CPEN), Computer Science (CPSC), Electrical Engineering (ELEN)",
      "POSITION LOCATION",
      "In Texas",
      "Desired Class Years",
      "Juniors, Seniors"
    ],
    "https": "//global.fujitsu/en-us/careers"
  },
  "event_details": {
    "content": [
      "Booth Location",
      "B26"
    ]
  },
  "all_text_content": "For StudentsFor Employers\nCareer Fairs / SEC Spring 2026 In-Person Engineering Career Fair\nSEC Spring 2026 In-Person Engineering Career Fair\nJan 28, 2026 - Jan 29, 2026\nLogin As A Student\nOverview\nAttending Employers\n1Finity, a Fujitsu Company\nInformation Technology/High Tech\nAttended Jan 29\nAbout\nhttps://global.fujitsu/en-us/careers View full profile View all jobs\nThe Fujitsu Group has operations in different regions around the world, including Japan, and provides digital services globally. We have built large-scale, cutting-edge systems that leverage our advanced technologies and extensive track record, garnering the No. 1 market share in Japan and a top-class position worldwide in the IT services field. As of July 1st 2025, Fujitsu consolidated its network business into a new company, 1Finity. A wholly owned subsidiary of Fujitsu, 1Finity combines decades of trusted experience with renewed innovation, agility, and customer success 1Finity, a Fujitsu company, is a global provider of communications networks for our connected world. We uniquely combine technological leadership and expertise in open optical and wireless networking, network automation, and applied AI/ML to design, build, operate, and maintain critical digital communications network infrastructure.\nWe Are Looking For\nIndustry\nEngineering\nDegree Levels Recruited\nBachelor's, Master's\nPosition Types\nFull-Time, Intern\nContact Information\nOrganization Name\n1Finity, a Fujitsu Company\nOrganization Profile\nWebsite\nhttps://global.fujitsu/en-us/careers\nOverview\nThe Fujitsu Group has operations in different regions around the world, including Japan, and provides digital services globally.\nWe have built large-scale, cutting-edge systems that leverage our advanced technologies and extensive track record, garnering the No. 1 market share in Japan and a top-class position worldwide in the IT services field.\n\nAs of July 1st 2025, Fujitsu consolidated its network business into a new company, 1Finity. A wholly owned subsidiary of Fujitsu, 1Finity combines decades of trusted experience with renewed innovation, agility, and customer success\n\n1Finity, a Fujitsu company, is a global provider of communications networks for our connected world. We uniquely combine technological leadership and expertise in open optical and wireless networking, network automation, and applied AI/ML to design, build, operate, and maintain critical digital communications network infrastructure.\nMajor(s) Recruited\nComputer Engineering (CPEN), Computer Science (CPSC), Electrical Engineering (ELEN)\nPOSITION LOCATION\nIn Texas\nDesired Class Years\nJuniors, Seniors\nBooth Location\nBooth Location\nB26\nWhen and Where\nJAN\n29\nDay 2 (Thursday, January 29th)\n9:00 AM - 5:00 PM\n2533 Midtown Pk Blvd Bryan, Texas 77801 United States\nCareer_Fair Students.View Booth Map\nPrivacy Policy | Terms of Use",
  "contact_info": {},
  "industry": "Engineering",
  "website": "https://global.fujitsu/en-us/careers",
  "position_types": [
    "Full-Time",
    "Intern"
  ],
  "majors_recruited": [
    "Computer Engineering (CPEN)",
    "Computer Science (CPSC)",
    "Electrical Engineering (ELEN)"
  ],
  "desired_class_years": [
    "Juniors",
    "Seniors"
  ],
  "booth_location": "B26",
  "all_sections": {
    "About": "https://global.fujitsu/en-us/careers View full profile View all jobs\nThe Fujitsu Group has operations in different regions around the world, including Japan, and provides digital services globally. We have built large-scale, cutting-edge systems that leverage our advanced technologies and extensive track record, garnering the No. 1 market share in Japan and a top-class position worldwide in the IT services field. As of July 1st 2025, Fujitsu consolidated its network business into a new company, 1Finity. A wholly owned subsidiary of Fujitsu, 1Finity combines decades of trusted experience with renewed innovation, agility, and customer success 1Finity, a Fujitsu company, is a global provider of communications networks for our connected world. We uniquely combine technological leadership and expertise in open optical and wireless networking, network automation, and applied AI/ML to design, build, operate, and maintain critical digital communications network infrastructure.",
    "We Are Looking For": "Industry\nEngineering\nDegree Levels Recruited\nBachelor's, Master's\nPosition Types\nFull-Time, Intern",
    "Contact Information": "Organization Name\n1Finity, a Fujitsu Company",
    "Organization Profile": "Website\nhttps://global.fujitsu/en-us/careers\nOverview\nThe Fujitsu Group has operations in different regions around the world, including Japan, and provides digital services globally.\nWe have built large-scale, cutting-edge systems that leverage our advanced technologies and extensive track record, garnering the No. 1 market share in Japan and a top-class position worldwide in the IT services field.\n\nAs of July 1st 2025, Fujitsu consolidated its network business into a new company, 1Finity. A wholly owned subsidiary of Fujitsu, 1Finity combines decades of trusted experience with renewed innovation, agility, and customer success\n\n1Finity, a Fujitsu company, is a global provider of communications networks for our connected world. We uniquely combine technological leadership and expertise in open optical and wireless networking, network automation, and applied AI/ML to design, build, operate, and maintain critical digital communications network infrastructure.\nMajor(s) Recruited\nComputer Engineering (CPEN), Computer Science (CPSC), Electrical Engineering (ELEN)\nPOSITION LOCATION\nIn Texas\nDesired Class Years\nJuniors, Seniors",
    "Booth Location": "Booth Location\nB26",
    "When and Where": "JAN\n29\nDay 2 (Thursday, January 29th)\n9:00 AM - 5:00 PM\n2533 Midtown Pk Blvd Bryan, Texas 77801 United States\nCareer_Fair Students.View Booth Map"
  }
}